<?xml version="1.0" ?>
<CommonRoadSolution benchmark_id="KS2:SM1:BEL_Beringen-8_1_T-1:2020a" computation_time="0.4681503709999788" date="2020-12-28">
  <ksTrajectory planningProblem="1">
    <ksState>
      <x>1000.9426</x>
      <y>873.36308</y>
      <steeringAngle>0.0</steeringAngle>
      <velocity>4.0</velocity>
      <orientation>-2.4333111</orientation>
      <time>0</time>
    </ksState>
    <ksState>
      <x>1000.6385688241957</x>
      <y>873.1031474686323</y>
      <steeringAngle>-0.035533333333333326</steeringAngle>
      <velocity>4.0</velocity>
      <orientation>-2.4360673745326005</orientation>
      <time>1</time>
    </ksState>
    <ksState>
      <x>1000.3331095527891</x>
      <y>872.844896213805</y>
      <steeringAngle>-0.07106666666666711</steeringAngle>
      <velocity>4.0</velocity>
      <orientation>-2.444343135075886</orientation>
      <time>2</time>
    </ksState>
    <ksState>
      <x>1000.0248184985012</x>
      <y>872.5900353271678</y>
      <steeringAngle>-0.10660000000000043</steeringAngle>
      <velocity>4.0</velocity>
      <orientation>-2.458159374895023</orientation>
      <time>3</time>
    </ksState>
    <ksState>
      <x>999.7123416973559</x>
      <y>872.3403290482314</y>
      <steeringAngle>-0.14213333333333378</steeringAngle>
      <velocity>4.0</velocity>
      <orientation>-2.4775513012805686</orientation>
      <time>4</time>
    </ksState>
    <ksState>
      <x>999.3944022047679</x>
      <y>872.0976232078559</y>
      <steeringAngle>-0.1776666666666672</steeringAngle>
      <velocity>4.0</velocity>
      <orientation>-2.502568707731966</orientation>
      <time>5</time>
    </ksState>
    <ksState>
      <x>999.102946060136</x>
      <y>871.886322996821</y>
      <steeringAngle>-0.1421333333333333</steeringAngle>
      <velocity>3.1999999999999993</velocity>
      <orientation>-2.5251786227054085</orientation>
      <time>6</time>
    </ksState>
    <ksState>
      <x>998.8733269589956</x>
      <y>871.7260924050995</y>
      <steeringAngle>-0.10659999999999997</steeringAngle>
      <velocity>2.3999999999999977</velocity>
      <orientation>-2.5388462635761155</orientation>
      <time>7</time>
    </ksState>
    <ksState>
      <x>998.7081491735108</x>
      <y>871.6133265676475</y>
      <steeringAngle>-0.07106666666666664</steeringAngle>
      <velocity>1.5999999999999976</velocity>
      <orientation>-2.5458469694293346</orientation>
      <time>8</time>
    </ksState>
    <ksState>
      <x>998.6087258780436</x>
      <y>871.5461328185343</y>
      <steeringAngle>-0.0355333333333333</steeringAngle>
      <velocity>0.7999999999999972</velocity>
      <orientation>-2.548421813903302</orientation>
      <time>9</time>
    </ksState>
    <ksState>
      <x>998.5755540574075</x>
      <y>871.5237804089003</y>
      <steeringAngle>2.5153490401663703e-17</steeringAngle>
      <velocity>-2.914335439641036e-15</velocity>
      <orientation>-2.5487893254818332</orientation>
      <time>10</time>
    </ksState>
    <ksState>
      <x>998.5423822371508</x>
      <y>871.5014279956407</y>
      <steeringAngle>0.03553333333333333</steeringAngle>
      <velocity>0.8</velocity>
      <orientation>-2.548421793703591</orientation>
      <time>11</time>
    </ksState>
    <ksState>
      <x>998.4429589472144</x>
      <y>871.4342342348251</y>
      <steeringAngle>0.0710666666666667</steeringAngle>
      <velocity>1.6</velocity>
      <orientation>-2.5458469471116056</orientation>
      <time>12</time>
    </ksState>
    <ksState>
      <x>998.277781173093</x>
      <y>871.3214683783141</y>
      <steeringAngle>0.10660000000000003</steeringAngle>
      <velocity>2.4000000000000004</velocity>
      <orientation>-2.5388462428747682</orientation>
      <time>13</time>
    </ksState>
    <ksState>
      <x>998.0481620850031</x>
      <y>871.1612377664661</y>
      <steeringAngle>0.14213333333333342</steeringAngle>
      <velocity>3.2000000000000015</velocity>
      <orientation>-2.5251786019339484</orientation>
      <time>14</time>
    </ksState>
    <ksState>
      <x>997.7567059472716</x>
      <y>870.9499375435851</y>
      <steeringAngle>0.17766666666666683</steeringAngle>
      <velocity>4.0000000000000036</velocity>
      <orientation>-2.502568686060728</orientation>
      <time>15</time>
    </ksState>
    <ksState>
      <x>997.4073083145345</x>
      <y>870.6825255586546</y>
      <steeringAngle>0.14213333333333333</steeringAngle>
      <velocity>4.8000000000000025</velocity>
      <orientation>-2.4751437863423753</orientation>
      <time>16</time>
    </ksState>
    <ksState>
      <x>997.0028544965502</x>
      <y>870.3557184288528</y>
      <steeringAngle>0.10660000000000003</steeringAngle>
      <velocity>5.600000000000005</velocity>
      <orientation>-2.4500275740634576</orientation>
      <time>17</time>
    </ksState>
    <ksState>
      <x>996.5449540437502</x>
      <y>869.9680144214226</y>
      <steeringAngle>0.07106666666666671</steeringAngle>
      <velocity>6.400000000000004</velocity>
      <orientation>-2.429395804463998</orientation>
      <time>18</time>
    </ksState>
    <ksState>
      <x>996.0337158258334</x>
      <y>869.5196530456478</y>
      <steeringAngle>0.035533333333333375</steeringAngle>
      <velocity>7.200000000000006</velocity>
      <orientation>-2.415419136371206</orientation>
      <time>19</time>
    </ksState>
    <ksState>
      <x>995.4671906294765</x>
      <y>869.0130488113332</y>
      <steeringAngle>2.6346112791397758e-17</steeringAngle>
      <velocity>8.000000000000007</velocity>
      <orientation>-2.410274123591637</orientation>
      <time>20</time>
    </ksState>
    <ksState>
      <x>994.8717550556922</x>
      <y>868.4787675394621</y>
      <steeringAngle>0.0</steeringAngle>
      <velocity>8.0</velocity>
      <orientation>-2.410274123591637</orientation>
      <time>21</time>
    </ksState>
    <ksState>
      <x>994.276319481908</x>
      <y>867.944486267591</y>
      <steeringAngle>0.0</steeringAngle>
      <velocity>8.0</velocity>
      <orientation>-2.410274123591637</orientation>
      <time>22</time>
    </ksState>
    <ksState>
      <x>993.6808839081237</x>
      <y>867.4102049957198</y>
      <steeringAngle>0.0</steeringAngle>
      <velocity>8.0</velocity>
      <orientation>-2.410274123591637</orientation>
      <time>23</time>
    </ksState>
    <ksState>
      <x>993.0854483343394</x>
      <y>866.8759237238487</y>
      <steeringAngle>0.0</steeringAngle>
      <velocity>8.0</velocity>
      <orientation>-2.410274123591637</orientation>
      <time>24</time>
    </ksState>
    <ksState>
      <x>992.4900127605551</x>
      <y>866.3416424519777</y>
      <steeringAngle>0.0</steeringAngle>
      <velocity>8.0</velocity>
      <orientation>-2.410274123591637</orientation>
      <time>25</time>
    </ksState>
    <ksState>
      <x>991.8945771867709</x>
      <y>865.8073611801066</y>
      <steeringAngle>0.0</steeringAngle>
      <velocity>8.0</velocity>
      <orientation>-2.410274123591637</orientation>
      <time>26</time>
    </ksState>
    <ksState>
      <x>991.2991416129867</x>
      <y>865.2730799082354</y>
      <steeringAngle>0.0</steeringAngle>
      <velocity>8.0</velocity>
      <orientation>-2.410274123591637</orientation>
      <time>27</time>
    </ksState>
    <ksState>
      <x>990.7037060392024</x>
      <y>864.7387986363643</y>
      <steeringAngle>0.0</steeringAngle>
      <velocity>8.0</velocity>
      <orientation>-2.410274123591637</orientation>
      <time>28</time>
    </ksState>
    <ksState>
      <x>990.1082704654181</x>
      <y>864.2045173644932</y>
      <steeringAngle>0.0</steeringAngle>
      <velocity>8.0</velocity>
      <orientation>-2.410274123591637</orientation>
      <time>29</time>
    </ksState>
    <ksState>
      <x>989.5128348916338</x>
      <y>863.6702360926222</y>
      <steeringAngle>0.0</steeringAngle>
      <velocity>8.0</velocity>
      <orientation>-2.410274123591637</orientation>
      <time>30</time>
    </ksState>
    <ksState>
      <x>988.9164194867245</x>
      <y>863.1370505137248</y>
      <steeringAngle>-0.03553333333333333</steeringAngle>
      <velocity>8.0</velocity>
      <orientation>-2.415786658594476</orientation>
      <time>31</time>
    </ksState>
    <ksState>
      <x>988.3141656815918</x>
      <y>862.610480827503</y>
      <steeringAngle>-0.07106666666666667</steeringAngle>
      <velocity>8.0</velocity>
      <orientation>-2.4323381794747454</orientation>
      <time>32</time>
    </ksState>
    <ksState>
      <x>987.7004417280446</x>
      <y>862.0973511376413</y>
      <steeringAngle>-0.10659999999999997</steeringAngle>
      <velocity>8.0</velocity>
      <orientation>-2.4599706587654406</orientation>
      <time>33</time>
    </ksState>
  </ksTrajectory>
</CommonRoadSolution>
